mcp_server_tapd/__init__.py
mcp_server_tapd/app_config.py
mcp_server_tapd/server.py
mcp_server_tapd/tapd.py
mcp_server_tapd-8.0.71.dist-info/METADATA
mcp_server_tapd-8.0.71.dist-info/WHEEL
mcp_server_tapd-8.0.71.dist-info/entry_points.txt
mcp_server_tapd-8.0.71.dist-info/top_level.txt
mcp_server_tapd-8.0.71.dist-info/RECORD
