Metadata-Version: 2.4
Name: mcp-server-tapd
Version: 8.0.71
Summary: TAPD MCP Server
Author-email: ryanjhzheng <zhengjianhong95@gmail.com>
Keywords: mcp,tapd
Requires-Python: >=3.13
Requires-Dist: httpx
Requires-Dist: requests
Requires-Dist: markdown
Requires-Dist: mcp[cli]>=1.0.0
